labelsmith/__init__.py
labelsmith/resources/macOS/macOS/AppIcon.appiconset/Contents.json
labelsmith/resources/macOS/macOS/AppIcon.appiconset/Icons.xcassets/LabelSTREAMIcon.appiconset/100.png
labelsmith/resources/macOS/macOS/AppIcon.appiconset/Icons.xcassets/LabelSTREAMIcon.appiconset/1024-mac.png
labelsmith/resources/macOS/macOS/AppIcon.appiconset/Icons.xcassets/LabelSTREAMIcon.appiconset/1024.png
labelsmith/resources/macOS/macOS/AppIcon.appiconset/Icons.xcassets/LabelSTREAMIcon.appiconset/114.png
labelsmith/resources/macOS/macOS/AppIcon.appiconset/Icons.xcassets/LabelSTREAMIcon.appiconset/120.png
labelsmith/resources/macOS/macOS/AppIcon.appiconset/Icons.xcassets/LabelSTREAMIcon.appiconset/128-mac.png
labelsmith/resources/macOS/macOS/AppIcon.appiconset/Icons.xcassets/LabelSTREAMIcon.appiconset/144.png
labelsmith/resources/macOS/macOS/AppIcon.appiconset/Icons.xcassets/LabelSTREAMIcon.appiconset/152.png
labelsmith/resources/macOS/macOS/AppIcon.appiconset/Icons.xcassets/LabelSTREAMIcon.appiconset/16-mac.png
labelsmith/resources/macOS/macOS/AppIcon.appiconset/Icons.xcassets/LabelSTREAMIcon.appiconset/167.png
labelsmith/resources/macOS/macOS/AppIcon.appiconset/Icons.xcassets/LabelSTREAMIcon.appiconset/172.png
labelsmith/resources/macOS/macOS/AppIcon.appiconset/Icons.xcassets/LabelSTREAMIcon.appiconset/180.png
labelsmith/resources/macOS/macOS/AppIcon.appiconset/Icons.xcassets/LabelSTREAMIcon.appiconset/196.png
labelsmith/resources/macOS/macOS/AppIcon.appiconset/Icons.xcassets/LabelSTREAMIcon.appiconset/20.png
labelsmith/resources/macOS/macOS/AppIcon.appiconset/Icons.xcassets/LabelSTREAMIcon.appiconset/216.png
labelsmith/resources/macOS/macOS/AppIcon.appiconset/Icons.xcassets/LabelSTREAMIcon.appiconset/256-mac.png
labelsmith/resources/macOS/macOS/AppIcon.appiconset/Icons.xcassets/LabelSTREAMIcon.appiconset/29.png
labelsmith/resources/macOS/macOS/AppIcon.appiconset/Icons.xcassets/LabelSTREAMIcon.appiconset/32-mac.png
labelsmith-0.0.1b8.dist-info/LICENSE
labelsmith-0.0.1b8.dist-info/METADATA
labelsmith-0.0.1b8.dist-info/WHEEL
labelsmith-0.0.1b8.dist-info/entry_points.txt
labelsmith-0.0.1b8.dist-info/RECORD
