Metadata-Version: 2.1
Name: labelsmith
Version: 0.0.1b8
Summary: A productivity suite for data annotators
License: Apache-2.0
Author: K. LeBryce
Author-email: k.lebryce@pm.me
Requires-Python: >=3.9,<3.13
Classifier: License :: OSI Approved :: Apache Software License
Classifier: Programming Language :: Python :: 3
Classifier: Programming Language :: Python :: 3.9
Classifier: Programming Language :: Python :: 3.10
Classifier: Programming Language :: Python :: 3.11
Classifier: Programming Language :: Python :: 3.12
Requires-Dist: appdirs (>=1.4.4,<2.0.0)
Requires-Dist: cryptography (>=43.0.0,<44.0.0)
Requires-Dist: matplotlib (>=3.9.1,<4.0.0)
Requires-Dist: mpld3 (>=0.5.10,<0.6.0)
Requires-Dist: nltk (>=3.8.1,<4.0.0)
Requires-Dist: pandas (>=2.2.2,<3.0.0)
Requires-Dist: pyinstaller (>=6.9.0,<7.0.0)
Requires-Dist: toml (>=0.10.2,<0.11.0)
Project-URL: Bug Tracker, https://github.com/kosmolebryce/labelsmith/issues
Project-URL: Homepage, https://github.com/kosmolebryce/labelsmith
